livewire/__init__.py
livewire/device_ip.py
livewire/find_port.py
livewire/httplib.py
livewire/reloader.py
livewire/server.py
livewire/wait_url.py
livewire/watch.py
livewire/webserver.py
livewire/filesystem_sync/__init__.py
livewire/filesystem_sync/any_observer.py
livewire/filesystem_sync/debouncer.py
livewire/filesystem_sync/debouncer_thread.py
livewire/filesystem_sync/sync_delta.py
livewire/filesystem_sync/sync_zip.py
livewire/filesystem_sync/watchdog_debouncer.py
livewire/filesystem_sync/watchdog_local.py
livewire-0.0.11.dist-info/METADATA
livewire-0.0.11.dist-info/WHEEL
livewire-0.0.11.dist-info/top_level.txt
livewire-0.0.11.dist-info/RECORD
