Metadata-Version: 2.1
Name: livewire
Version: 0.0.11
Author-email: Simone Giacomelli <simone.giacomelli@gmail.com>
Project-URL: Homepage, https://github.com/simonegiacomelli/livewire
Project-URL: Issues, https://github.com/simonegiacomelli/livewire/issues
Keywords: livewire,development,tools
Classifier: Intended Audience :: Developers
Classifier: Programming Language :: Python :: 3
Requires-Python: >=3.8
Requires-Dist: watchdog ==4.0.1
Provides-Extra: pypi
Requires-Dist: twine ; extra == 'pypi'
Requires-Dist: build ; extra == 'pypi'
Provides-Extra: test
Requires-Dist: pytest ; extra == 'test'
